brazilian_register/__init__.py
brazilian_register/cnpj/__init__.py
brazilian_register/cnpj/cnpj_tools.py
brazilian_register/cpf/__init__.py
brazilian_register/cpf/cpf_tools.py
brazilian_register-0.0.4.dist-info/METADATA
brazilian_register-0.0.4.dist-info/WHEEL
brazilian_register-0.0.4.dist-info/top_level.txt
brazilian_register-0.0.4.dist-info/RECORD
