Metadata-Version: 2.1
Name: brazilian-register
Version: 0.0.4
Summary: Tools to test brazilian register numbers (CPF or CNPJ)
Home-page: https://github.com/silvamathias/dio_desafio_ciacao_pacote_python
Author: Phelipe Mathias
Author-email: silvamathias@gmail.com
License: UNKNOWN
Platform: UNKNOWN
Requires-Python: >=3.7
Requires-Dist: numpy
